{
    "predictions": [
        {
            "x": 165,
            "y": 118,
            "width": 85,
            "height": 76,
            "confidence": 0.9479473829269409,
            "class": "Not Staff",
            "class_id": 0,
            "image_path": "C:\\Program Files (x86)\\Work\\FootfallCam\\data\\video_frame\\TBD\\Images_ED2\\frame1041_ori.png",
            "prediction_type": "ObjectDetectionModel"
        },
        {
            "x": 163,
            "y": 573,
            "width": 111,
            "height": 77,
            "confidence": 0.9438961744308472,
            "class": "Not Staff",
            "class_id": 0,
            "image_path": "C:\\Program Files (x86)\\Work\\FootfallCam\\data\\video_frame\\TBD\\Images_ED2\\frame1041_ori.png",
            "prediction_type": "ObjectDetectionModel"
        },
        {
            "x": 749,
            "y": 497,
            "width": 91,
            "height": 91,
            "confidence": 0.9406179189682007,
            "class": "Not Staff",
            "class_id": 0,
            "image_path": "C:\\Program Files (x86)\\Work\\FootfallCam\\data\\video_frame\\TBD\\Images_ED2\\frame1041_ori.png",
            "prediction_type": "ObjectDetectionModel"
        },
        {
            "x": 462,
            "y": 52,
            "width": 84,
            "height": 105,
            "confidence": 0.9398713111877441,
            "class": "Not Staff",
            "class_id": 0,
            "image_path": "C:\\Program Files (x86)\\Work\\FootfallCam\\data\\video_frame\\TBD\\Images_ED2\\frame1041_ori.png",
            "prediction_type": "ObjectDetectionModel"
        },
        {
            "x": 740,
            "y": 359,
            "width": 103,
            "height": 100,
            "confidence": 0.9360679388046265,
            "class": "Not Staff",
            "class_id": 0,
            "image_path": "C:\\Program Files (x86)\\Work\\FootfallCam\\data\\video_frame\\TBD\\Images_ED2\\frame1041_ori.png",
            "prediction_type": "ObjectDetectionModel"
        },
        {
            "x": 720,
            "y": 632,
            "width": 76,
            "height": 76,
            "confidence": 0.9301236867904663,
            "class": "Not Staff",
            "class_id": 0,
            "image_path": "C:\\Program Files (x86)\\Work\\FootfallCam\\data\\video_frame\\TBD\\Images_ED2\\frame1041_ori.png",
            "prediction_type": "ObjectDetectionModel"
        },
        {
            "x": 365,
            "y": 142,
            "width": 106,
            "height": 113,
            "confidence": 0.9296667575836182,
            "class": "Not Staff",
            "class_id": 0,
            "image_path": "C:\\Program Files (x86)\\Work\\FootfallCam\\data\\video_frame\\TBD\\Images_ED2\\frame1041_ori.png",
            "prediction_type": "ObjectDetectionModel"
        },
        {
            "x": 600,
            "y": 677,
            "width": 79,
            "height": 84,
            "confidence": 0.9222217798233032,
            "class": "Not Staff",
            "class_id": 0,
            "image_path": "C:\\Program Files (x86)\\Work\\FootfallCam\\data\\video_frame\\TBD\\Images_ED2\\frame1041_ori.png",
            "prediction_type": "ObjectDetectionModel"
        },
        {
            "x": 261,
            "y": 86,
            "width": 85,
            "height": 103,
            "confidence": 0.9178416132926941,
            "class": "Not Staff",
            "class_id": 0,
            "image_path": "C:\\Program Files (x86)\\Work\\FootfallCam\\data\\video_frame\\TBD\\Images_ED2\\frame1041_ori.png",
            "prediction_type": "ObjectDetectionModel"
        },
        {
            "x": 265,
            "y": 623,
            "width": 69,
            "height": 102,
            "confidence": 0.9177761673927307,
            "class": "Not Staff",
            "class_id": 0,
            "image_path": "C:\\Program Files (x86)\\Work\\FootfallCam\\data\\video_frame\\TBD\\Images_ED2\\frame1041_ori.png",
            "prediction_type": "ObjectDetectionModel"
        },
        {
            "x": 741,
            "y": 187,
            "width": 90,
            "height": 88,
            "confidence": 0.9099609851837158,
            "class": "Not Staff",
            "class_id": 0,
            "image_path": "C:\\Program Files (x86)\\Work\\FootfallCam\\data\\video_frame\\TBD\\Images_ED2\\frame1041_ori.png",
            "prediction_type": "ObjectDetectionModel"
        },
        {
            "x": 260,
            "y": 188,
            "width": 91,
            "height": 86,
            "confidence": 0.9024853110313416,
            "class": "Not Staff",
            "class_id": 0,
            "image_path": "C:\\Program Files (x86)\\Work\\FootfallCam\\data\\video_frame\\TBD\\Images_ED2\\frame1041_ori.png",
            "prediction_type": "ObjectDetectionModel"
        },
        {
            "x": 137,
            "y": 205,
            "width": 58,
            "height": 60,
            "confidence": 0.8941562175750732,
            "class": "Not Staff",
            "class_id": 0,
            "image_path": "C:\\Program Files (x86)\\Work\\FootfallCam\\data\\video_frame\\TBD\\Images_ED2\\frame1041_ori.png",
            "prediction_type": "ObjectDetectionModel"
        },
        {
            "x": 511,
            "y": 559,
            "width": 105,
            "height": 219,
            "confidence": 0.893017053604126,
            "class": "Not Staff",
            "class_id": 0,
            "image_path": "C:\\Program Files (x86)\\Work\\FootfallCam\\data\\video_frame\\TBD\\Images_ED2\\frame1041_ori.png",
            "prediction_type": "ObjectDetectionModel"
        },
        {
            "x": 340,
            "y": 636,
            "width": 75,
            "height": 113,
            "confidence": 0.8832311630249023,
            "class": "Not Staff",
            "class_id": 0,
            "image_path": "C:\\Program Files (x86)\\Work\\FootfallCam\\data\\video_frame\\TBD\\Images_ED2\\frame1041_ori.png",
            "prediction_type": "ObjectDetectionModel"
        },
        {
            "x": 192,
            "y": 198,
            "width": 69,
            "height": 83,
            "confidence": 0.8798288106918335,
            "class": "Not Staff",
            "class_id": 0,
            "image_path": "C:\\Program Files (x86)\\Work\\FootfallCam\\data\\video_frame\\TBD\\Images_ED2\\frame1041_ori.png",
            "prediction_type": "ObjectDetectionModel"
        },
        {
            "x": 604,
            "y": 529,
            "width": 111,
            "height": 142,
            "confidence": 0.8272044658660889,
            "class": "Not Staff",
            "class_id": 0,
            "image_path": "C:\\Program Files (x86)\\Work\\FootfallCam\\data\\video_frame\\TBD\\Images_ED2\\frame1041_ori.png",
            "prediction_type": "ObjectDetectionModel"
        }
    ],
    "image": {
        "width": "960",
        "height": "720"
    }
}