{
    "predictions": [
        {
            "x": 163,
            "y": 573,
            "width": 111,
            "height": 77,
            "confidence": 0.9427523016929626,
            "class": "Not Staff",
            "class_id": 0,
            "image_path": "C:\\Program Files (x86)\\Work\\FootfallCam\\data\\video_frame\\TBD\\Images_ED3\\frame1177_ori.png",
            "prediction_type": "ObjectDetectionModel"
        },
        {
            "x": 336,
            "y": 629,
            "width": 75,
            "height": 102,
            "confidence": 0.9351070523262024,
            "class": "Not Staff",
            "class_id": 0,
            "image_path": "C:\\Program Files (x86)\\Work\\FootfallCam\\data\\video_frame\\TBD\\Images_ED3\\frame1177_ori.png",
            "prediction_type": "ObjectDetectionModel"
        },
        {
            "x": 740,
            "y": 361,
            "width": 103,
            "height": 99,
            "confidence": 0.9300493001937866,
            "class": "Not Staff",
            "class_id": 0,
            "image_path": "C:\\Program Files (x86)\\Work\\FootfallCam\\data\\video_frame\\TBD\\Images_ED3\\frame1177_ori.png",
            "prediction_type": "ObjectDetectionModel"
        },
        {
            "x": 603,
            "y": 677,
            "width": 82,
            "height": 84,
            "confidence": 0.9289042949676514,
            "class": "Not Staff",
            "class_id": 0,
            "image_path": "C:\\Program Files (x86)\\Work\\FootfallCam\\data\\video_frame\\TBD\\Images_ED3\\frame1177_ori.png",
            "prediction_type": "ObjectDetectionModel"
        },
        {
            "x": 262,
            "y": 618,
            "width": 69,
            "height": 102,
            "confidence": 0.9287668466567993,
            "class": "Not Staff",
            "class_id": 0,
            "image_path": "C:\\Program Files (x86)\\Work\\FootfallCam\\data\\video_frame\\TBD\\Images_ED3\\frame1177_ori.png",
            "prediction_type": "ObjectDetectionModel"
        },
        {
            "x": 466,
            "y": 52,
            "width": 78,
            "height": 105,
            "confidence": 0.9280649423599243,
            "class": "Not Staff",
            "class_id": 0,
            "image_path": "C:\\Program Files (x86)\\Work\\FootfallCam\\data\\video_frame\\TBD\\Images_ED3\\frame1177_ori.png",
            "prediction_type": "ObjectDetectionModel"
        },
        {
            "x": 745,
            "y": 193,
            "width": 96,
            "height": 83,
            "confidence": 0.9233193397521973,
            "class": "Not Staff",
            "class_id": 0,
            "image_path": "C:\\Program Files (x86)\\Work\\FootfallCam\\data\\video_frame\\TBD\\Images_ED3\\frame1177_ori.png",
            "prediction_type": "ObjectDetectionModel"
        },
        {
            "x": 721,
            "y": 632,
            "width": 78,
            "height": 78,
            "confidence": 0.9232459664344788,
            "class": "Not Staff",
            "class_id": 0,
            "image_path": "C:\\Program Files (x86)\\Work\\FootfallCam\\data\\video_frame\\TBD\\Images_ED3\\frame1177_ori.png",
            "prediction_type": "ObjectDetectionModel"
        },
        {
            "x": 364,
            "y": 139,
            "width": 99,
            "height": 117,
            "confidence": 0.9225462675094604,
            "class": "Not Staff",
            "class_id": 0,
            "image_path": "C:\\Program Files (x86)\\Work\\FootfallCam\\data\\video_frame\\TBD\\Images_ED3\\frame1177_ori.png",
            "prediction_type": "ObjectDetectionModel"
        },
        {
            "x": 257,
            "y": 189,
            "width": 97,
            "height": 87,
            "confidence": 0.9195023775100708,
            "class": "Not Staff",
            "class_id": 0,
            "image_path": "C:\\Program Files (x86)\\Work\\FootfallCam\\data\\video_frame\\TBD\\Images_ED3\\frame1177_ori.png",
            "prediction_type": "ObjectDetectionModel"
        },
        {
            "x": 554,
            "y": 257,
            "width": 112,
            "height": 182,
            "confidence": 0.9150422811508179,
            "class": "Not Staff",
            "class_id": 0,
            "image_path": "C:\\Program Files (x86)\\Work\\FootfallCam\\data\\video_frame\\TBD\\Images_ED3\\frame1177_ori.png",
            "prediction_type": "ObjectDetectionModel"
        },
        {
            "x": 264,
            "y": 86,
            "width": 87,
            "height": 101,
            "confidence": 0.9067896604537964,
            "class": "Not Staff",
            "class_id": 0,
            "image_path": "C:\\Program Files (x86)\\Work\\FootfallCam\\data\\video_frame\\TBD\\Images_ED3\\frame1177_ori.png",
            "prediction_type": "ObjectDetectionModel"
        },
        {
            "x": 626,
            "y": 528,
            "width": 100,
            "height": 112,
            "confidence": 0.8977779150009155,
            "class": "Not Staff",
            "class_id": 0,
            "image_path": "C:\\Program Files (x86)\\Work\\FootfallCam\\data\\video_frame\\TBD\\Images_ED3\\frame1177_ori.png",
            "prediction_type": "ObjectDetectionModel"
        },
        {
            "x": 193,
            "y": 190,
            "width": 63,
            "height": 78,
            "confidence": 0.8807756900787354,
            "class": "Not Staff",
            "class_id": 0,
            "image_path": "C:\\Program Files (x86)\\Work\\FootfallCam\\data\\video_frame\\TBD\\Images_ED3\\frame1177_ori.png",
            "prediction_type": "ObjectDetectionModel"
        },
        {
            "x": 138,
            "y": 202,
            "width": 61,
            "height": 60,
            "confidence": 0.8530049324035645,
            "class": "Not Staff",
            "class_id": 0,
            "image_path": "C:\\Program Files (x86)\\Work\\FootfallCam\\data\\video_frame\\TBD\\Images_ED3\\frame1177_ori.png",
            "prediction_type": "ObjectDetectionModel"
        },
        {
            "x": 194,
            "y": 111,
            "width": 73,
            "height": 82,
            "confidence": 0.6023986339569092,
            "class": "Not Staff",
            "class_id": 0,
            "image_path": "C:\\Program Files (x86)\\Work\\FootfallCam\\data\\video_frame\\TBD\\Images_ED3\\frame1177_ori.png",
            "prediction_type": "ObjectDetectionModel"
        },
        {
            "x": 144,
            "y": 116,
            "width": 48,
            "height": 66,
            "confidence": 0.5038761496543884,
            "class": "Not Staff",
            "class_id": 0,
            "image_path": "C:\\Program Files (x86)\\Work\\FootfallCam\\data\\video_frame\\TBD\\Images_ED3\\frame1177_ori.png",
            "prediction_type": "ObjectDetectionModel"
        }
    ],
    "image": {
        "width": "960",
        "height": "720"
    }
}