{
    "predictions": [
        {
            "x": 468,
            "y": 53,
            "width": 75,
            "height": 106,
            "confidence": 0.9730397462844849,
            "class": "Not Staff",
            "class_confidence": null,
            "class_id": 0,
            "tracker_id": null,
            "image_path": "C:\\Program Files (x86)\\Work\\FootfallCam\\data\\video_frame\\TBD\\images_20fps\\frame0390_ori.png",
            "prediction_type": "ObjectDetectionModel"
        },
        {
            "x": 570,
            "y": 64,
            "width": 82,
            "height": 119,
            "confidence": 0.9426933526992798,
            "class": "Not Staff",
            "class_confidence": null,
            "class_id": 0,
            "tracker_id": null,
            "image_path": "C:\\Program Files (x86)\\Work\\FootfallCam\\data\\video_frame\\TBD\\images_20fps\\frame0390_ori.png",
            "prediction_type": "ObjectDetectionModel"
        },
        {
            "x": 255,
            "y": 95,
            "width": 93,
            "height": 91,
            "confidence": 0.912885308265686,
            "class": "Not Staff",
            "class_confidence": null,
            "class_id": 0,
            "tracker_id": null,
            "image_path": "C:\\Program Files (x86)\\Work\\FootfallCam\\data\\video_frame\\TBD\\images_20fps\\frame0390_ori.png",
            "prediction_type": "ObjectDetectionModel"
        },
        {
            "x": 255,
            "y": 181,
            "width": 75,
            "height": 87,
            "confidence": 0.909895658493042,
            "class": "Not Staff",
            "class_confidence": null,
            "class_id": 0,
            "tracker_id": null,
            "image_path": "C:\\Program Files (x86)\\Work\\FootfallCam\\data\\video_frame\\TBD\\images_20fps\\frame0390_ori.png",
            "prediction_type": "ObjectDetectionModel"
        },
        {
            "x": 333,
            "y": 165,
            "width": 93,
            "height": 84,
            "confidence": 0.8999806642532349,
            "class": "Not Staff",
            "class_confidence": null,
            "class_id": 0,
            "tracker_id": null,
            "image_path": "C:\\Program Files (x86)\\Work\\FootfallCam\\data\\video_frame\\TBD\\images_20fps\\frame0390_ori.png",
            "prediction_type": "ObjectDetectionModel"
        },
        {
            "x": 166,
            "y": 117,
            "width": 90,
            "height": 69,
            "confidence": 0.8875380754470825,
            "class": "Not Staff",
            "class_confidence": null,
            "class_id": 0,
            "tracker_id": null,
            "image_path": "C:\\Program Files (x86)\\Work\\FootfallCam\\data\\video_frame\\TBD\\images_20fps\\frame0390_ori.png",
            "prediction_type": "ObjectDetectionModel"
        },
        {
            "x": 744,
            "y": 199,
            "width": 87,
            "height": 81,
            "confidence": 0.8866455554962158,
            "class": "Not Staff",
            "class_confidence": null,
            "class_id": 0,
            "tracker_id": null,
            "image_path": "C:\\Program Files (x86)\\Work\\FootfallCam\\data\\video_frame\\TBD\\images_20fps\\frame0390_ori.png",
            "prediction_type": "ObjectDetectionModel"
        },
        {
            "x": 164,
            "y": 574,
            "width": 115,
            "height": 76,
            "confidence": 0.8826644420623779,
            "class": "Not Staff",
            "class_confidence": null,
            "class_id": 0,
            "tracker_id": null,
            "image_path": "C:\\Program Files (x86)\\Work\\FootfallCam\\data\\video_frame\\TBD\\images_20fps\\frame0390_ori.png",
            "prediction_type": "ObjectDetectionModel"
        },
        {
            "x": 651,
            "y": 360,
            "width": 88,
            "height": 133,
            "confidence": 0.8699041604995728,
            "class": "Not Staff",
            "class_confidence": null,
            "class_id": 0,
            "tracker_id": null,
            "image_path": "C:\\Program Files (x86)\\Work\\FootfallCam\\data\\video_frame\\TBD\\images_20fps\\frame0390_ori.png",
            "prediction_type": "ObjectDetectionModel"
        },
        {
            "x": 336,
            "y": 622,
            "width": 79,
            "height": 99,
            "confidence": 0.8668211102485657,
            "class": "Not Staff",
            "class_confidence": null,
            "class_id": 0,
            "tracker_id": null,
            "image_path": "C:\\Program Files (x86)\\Work\\FootfallCam\\data\\video_frame\\TBD\\images_20fps\\frame0390_ori.png",
            "prediction_type": "ObjectDetectionModel"
        },
        {
            "x": 622,
            "y": 535,
            "width": 105,
            "height": 117,
            "confidence": 0.8666669130325317,
            "class": "Not Staff",
            "class_confidence": null,
            "class_id": 0,
            "tracker_id": null,
            "image_path": "C:\\Program Files (x86)\\Work\\FootfallCam\\data\\video_frame\\TBD\\images_20fps\\frame0390_ori.png",
            "prediction_type": "ObjectDetectionModel"
        },
        {
            "x": 750,
            "y": 500,
            "width": 94,
            "height": 88,
            "confidence": 0.8543227910995483,
            "class": "Not Staff",
            "class_confidence": null,
            "class_id": 0,
            "tracker_id": null,
            "image_path": "C:\\Program Files (x86)\\Work\\FootfallCam\\data\\video_frame\\TBD\\images_20fps\\frame0390_ori.png",
            "prediction_type": "ObjectDetectionModel"
        },
        {
            "x": 750,
            "y": 360,
            "width": 87,
            "height": 102,
            "confidence": 0.8361769914627075,
            "class": "Not Staff",
            "class_confidence": null,
            "class_id": 0,
            "tracker_id": null,
            "image_path": "C:\\Program Files (x86)\\Work\\FootfallCam\\data\\video_frame\\TBD\\images_20fps\\frame0390_ori.png",
            "prediction_type": "ObjectDetectionModel"
        },
        {
            "x": 141,
            "y": 212,
            "width": 67,
            "height": 57,
            "confidence": 0.8324244022369385,
            "class": "Not Staff",
            "class_confidence": null,
            "class_id": 0,
            "tracker_id": null,
            "image_path": "C:\\Program Files (x86)\\Work\\FootfallCam\\data\\video_frame\\TBD\\images_20fps\\frame0390_ori.png",
            "prediction_type": "ObjectDetectionModel"
        },
        {
            "x": 604,
            "y": 667,
            "width": 84,
            "height": 92,
            "confidence": 0.8307185173034668,
            "class": "Not Staff",
            "class_confidence": null,
            "class_id": 0,
            "tracker_id": null,
            "image_path": "C:\\Program Files (x86)\\Work\\FootfallCam\\data\\video_frame\\TBD\\images_20fps\\frame0390_ori.png",
            "prediction_type": "ObjectDetectionModel"
        },
        {
            "x": 189,
            "y": 180,
            "width": 72,
            "height": 81,
            "confidence": 0.8269859552383423,
            "class": "Not Staff",
            "class_confidence": null,
            "class_id": 0,
            "tracker_id": null,
            "image_path": "C:\\Program Files (x86)\\Work\\FootfallCam\\data\\video_frame\\TBD\\images_20fps\\frame0390_ori.png",
            "prediction_type": "ObjectDetectionModel"
        },
        {
            "x": 261,
            "y": 617,
            "width": 64,
            "height": 95,
            "confidence": 0.8225442171096802,
            "class": "Not Staff",
            "class_confidence": null,
            "class_id": 0,
            "tracker_id": null,
            "image_path": "C:\\Program Files (x86)\\Work\\FootfallCam\\data\\video_frame\\TBD\\images_20fps\\frame0390_ori.png",
            "prediction_type": "ObjectDetectionModel"
        },
        {
            "x": 723,
            "y": 631,
            "width": 81,
            "height": 79,
            "confidence": 0.8012020587921143,
            "class": "Not Staff",
            "class_confidence": null,
            "class_id": 0,
            "tracker_id": null,
            "image_path": "C:\\Program Files (x86)\\Work\\FootfallCam\\data\\video_frame\\TBD\\images_20fps\\frame0390_ori.png",
            "prediction_type": "ObjectDetectionModel"
        },
        {
            "x": 563,
            "y": 249,
            "width": 109,
            "height": 153,
            "confidence": 0.7027482390403748,
            "class": "Not Staff",
            "class_confidence": null,
            "class_id": 0,
            "tracker_id": null,
            "image_path": "C:\\Program Files (x86)\\Work\\FootfallCam\\data\\video_frame\\TBD\\images_20fps\\frame0390_ori.png",
            "prediction_type": "ObjectDetectionModel"
        }
    ],
    "image": {
        "width": "960",
        "height": "720"
    }
}