{
    "predictions": [
        {
            "x": 465,
            "y": 54,
            "width": 78,
            "height": 108,
            "confidence": 0.9704777002334595,
            "class": "Not Staff",
            "class_confidence": null,
            "class_id": 0,
            "tracker_id": null,
            "image_path": "C:\\Program Files (x86)\\Work\\FootfallCam\\data\\video_frame\\TBD\\images_20fps\\frame0286_ori.png",
            "prediction_type": "ObjectDetectionModel"
        },
        {
            "x": 260,
            "y": 90,
            "width": 88,
            "height": 100,
            "confidence": 0.9541573524475098,
            "class": "Not Staff",
            "class_confidence": null,
            "class_id": 0,
            "tracker_id": null,
            "image_path": "C:\\Program Files (x86)\\Work\\FootfallCam\\data\\video_frame\\TBD\\images_20fps\\frame0286_ori.png",
            "prediction_type": "ObjectDetectionModel"
        },
        {
            "x": 570,
            "y": 63,
            "width": 82,
            "height": 119,
            "confidence": 0.9440324902534485,
            "class": "Not Staff",
            "class_confidence": null,
            "class_id": 0,
            "tracker_id": null,
            "image_path": "C:\\Program Files (x86)\\Work\\FootfallCam\\data\\video_frame\\TBD\\images_20fps\\frame0286_ori.png",
            "prediction_type": "ObjectDetectionModel"
        },
        {
            "x": 259,
            "y": 181,
            "width": 93,
            "height": 84,
            "confidence": 0.9357023239135742,
            "class": "Not Staff",
            "class_confidence": null,
            "class_id": 0,
            "tracker_id": null,
            "image_path": "C:\\Program Files (x86)\\Work\\FootfallCam\\data\\video_frame\\TBD\\images_20fps\\frame0286_ori.png",
            "prediction_type": "ObjectDetectionModel"
        },
        {
            "x": 166,
            "y": 118,
            "width": 87,
            "height": 74,
            "confidence": 0.9020175933837891,
            "class": "Not Staff",
            "class_confidence": null,
            "class_id": 0,
            "tracker_id": null,
            "image_path": "C:\\Program Files (x86)\\Work\\FootfallCam\\data\\video_frame\\TBD\\images_20fps\\frame0286_ori.png",
            "prediction_type": "ObjectDetectionModel"
        },
        {
            "x": 336,
            "y": 621,
            "width": 76,
            "height": 100,
            "confidence": 0.90062415599823,
            "class": "Not Staff",
            "class_confidence": null,
            "class_id": 0,
            "tracker_id": null,
            "image_path": "C:\\Program Files (x86)\\Work\\FootfallCam\\data\\video_frame\\TBD\\images_20fps\\frame0286_ori.png",
            "prediction_type": "ObjectDetectionModel"
        },
        {
            "x": 649,
            "y": 362,
            "width": 87,
            "height": 129,
            "confidence": 0.8897691965103149,
            "class": "Not Staff",
            "class_confidence": null,
            "class_id": 0,
            "tracker_id": null,
            "image_path": "C:\\Program Files (x86)\\Work\\FootfallCam\\data\\video_frame\\TBD\\images_20fps\\frame0286_ori.png",
            "prediction_type": "ObjectDetectionModel"
        },
        {
            "x": 743,
            "y": 197,
            "width": 88,
            "height": 79,
            "confidence": 0.8796780109405518,
            "class": "Not Staff",
            "class_confidence": null,
            "class_id": 0,
            "tracker_id": null,
            "image_path": "C:\\Program Files (x86)\\Work\\FootfallCam\\data\\video_frame\\TBD\\images_20fps\\frame0286_ori.png",
            "prediction_type": "ObjectDetectionModel"
        },
        {
            "x": 747,
            "y": 358,
            "width": 91,
            "height": 110,
            "confidence": 0.8722714185714722,
            "class": "Not Staff",
            "class_confidence": null,
            "class_id": 0,
            "tracker_id": null,
            "image_path": "C:\\Program Files (x86)\\Work\\FootfallCam\\data\\video_frame\\TBD\\images_20fps\\frame0286_ori.png",
            "prediction_type": "ObjectDetectionModel"
        },
        {
            "x": 339,
            "y": 162,
            "width": 79,
            "height": 86,
            "confidence": 0.870427131652832,
            "class": "Not Staff",
            "class_confidence": null,
            "class_id": 0,
            "tracker_id": null,
            "image_path": "C:\\Program Files (x86)\\Work\\FootfallCam\\data\\video_frame\\TBD\\images_20fps\\frame0286_ori.png",
            "prediction_type": "ObjectDetectionModel"
        },
        {
            "x": 750,
            "y": 500,
            "width": 96,
            "height": 91,
            "confidence": 0.8641126155853271,
            "class": "Not Staff",
            "class_confidence": null,
            "class_id": 0,
            "tracker_id": null,
            "image_path": "C:\\Program Files (x86)\\Work\\FootfallCam\\data\\video_frame\\TBD\\images_20fps\\frame0286_ori.png",
            "prediction_type": "ObjectDetectionModel"
        },
        {
            "x": 620,
            "y": 534,
            "width": 97,
            "height": 117,
            "confidence": 0.8552989959716797,
            "class": "Not Staff",
            "class_confidence": null,
            "class_id": 0,
            "tracker_id": null,
            "image_path": "C:\\Program Files (x86)\\Work\\FootfallCam\\data\\video_frame\\TBD\\images_20fps\\frame0286_ori.png",
            "prediction_type": "ObjectDetectionModel"
        },
        {
            "x": 219,
            "y": 487,
            "width": 96,
            "height": 102,
            "confidence": 0.8516054153442383,
            "class": "Not Staff",
            "class_confidence": null,
            "class_id": 0,
            "tracker_id": null,
            "image_path": "C:\\Program Files (x86)\\Work\\FootfallCam\\data\\video_frame\\TBD\\images_20fps\\frame0286_ori.png",
            "prediction_type": "ObjectDetectionModel"
        },
        {
            "x": 604,
            "y": 666,
            "width": 84,
            "height": 91,
            "confidence": 0.8388204574584961,
            "class": "Not Staff",
            "class_confidence": null,
            "class_id": 0,
            "tracker_id": null,
            "image_path": "C:\\Program Files (x86)\\Work\\FootfallCam\\data\\video_frame\\TBD\\images_20fps\\frame0286_ori.png",
            "prediction_type": "ObjectDetectionModel"
        },
        {
            "x": 163,
            "y": 573,
            "width": 114,
            "height": 81,
            "confidence": 0.8276498913764954,
            "class": "Not Staff",
            "class_confidence": null,
            "class_id": 0,
            "tracker_id": null,
            "image_path": "C:\\Program Files (x86)\\Work\\FootfallCam\\data\\video_frame\\TBD\\images_20fps\\frame0286_ori.png",
            "prediction_type": "ObjectDetectionModel"
        },
        {
            "x": 723,
            "y": 632,
            "width": 78,
            "height": 78,
            "confidence": 0.8043805360794067,
            "class": "Not Staff",
            "class_confidence": null,
            "class_id": 0,
            "tracker_id": null,
            "image_path": "C:\\Program Files (x86)\\Work\\FootfallCam\\data\\video_frame\\TBD\\images_20fps\\frame0286_ori.png",
            "prediction_type": "ObjectDetectionModel"
        },
        {
            "x": 263,
            "y": 610,
            "width": 64,
            "height": 93,
            "confidence": 0.7840943932533264,
            "class": "Not Staff",
            "class_confidence": null,
            "class_id": 0,
            "tracker_id": null,
            "image_path": "C:\\Program Files (x86)\\Work\\FootfallCam\\data\\video_frame\\TBD\\images_20fps\\frame0286_ori.png",
            "prediction_type": "ObjectDetectionModel"
        },
        {
            "x": 119,
            "y": 426,
            "width": 91,
            "height": 83,
            "confidence": 0.7367498874664307,
            "class": "Not Staff",
            "class_confidence": null,
            "class_id": 0,
            "tracker_id": null,
            "image_path": "C:\\Program Files (x86)\\Work\\FootfallCam\\data\\video_frame\\TBD\\images_20fps\\frame0286_ori.png",
            "prediction_type": "ObjectDetectionModel"
        },
        {
            "x": 187,
            "y": 189,
            "width": 66,
            "height": 81,
            "confidence": 0.7162790894508362,
            "class": "Not Staff",
            "class_confidence": null,
            "class_id": 0,
            "tracker_id": null,
            "image_path": "C:\\Program Files (x86)\\Work\\FootfallCam\\data\\video_frame\\TBD\\images_20fps\\frame0286_ori.png",
            "prediction_type": "ObjectDetectionModel"
        },
        {
            "x": 136,
            "y": 212,
            "width": 60,
            "height": 52,
            "confidence": 0.6879359483718872,
            "class": "Not Staff",
            "class_confidence": null,
            "class_id": 0,
            "tracker_id": null,
            "image_path": "C:\\Program Files (x86)\\Work\\FootfallCam\\data\\video_frame\\TBD\\images_20fps\\frame0286_ori.png",
            "prediction_type": "ObjectDetectionModel"
        }
    ],
    "image": {
        "width": "960",
        "height": "720"
    }
}